pymli/__init__.py
pymli/models/__init__.py
pymli/models/ae.py
pymli/models/base.py
pymli/models/iforest.py
pymli/models/knn.py
pymli/models/mixins.py
pymli/models/ocsvm.py
pymli/models/vae.py
pymli/models/layers/__init__.py
pymli/models/layers/kldivergence.py
pymli/preprocessing/__init__.py
pymli/preprocessing/label_binarizer.py
pymli/utils/__init__.py
pymli/utils/decorators.py
pymli/utils/stats_models.py
pymli/utils/utility.py
pymli/visualization/__init__.py
pymli/visualization/graphs.py
pymli-0.0.9.dist-info/LICENSE
pymli-0.0.9.dist-info/METADATA
pymli-0.0.9.dist-info/WHEEL
pymli-0.0.9.dist-info/top_level.txt
pymli-0.0.9.dist-info/RECORD
