Metadata-Version: 2.1
Name: pymli
Version: 0.0.9
Summary: A Python Machine Learning Library
Home-page: https://github.com/flianza/pymli
Author: Franco Lianza
Author-email: lianza.fl@gmail.com
License: UNKNOWN
Keywords: outlier detection,anomaly detection,machine learning,neural networks
Platform: UNKNOWN
Classifier: Programming Language :: Python :: 3
Classifier: License :: OSI Approved :: MIT License
Classifier: Operating System :: OS Independent
Requires-Dist: scipy (>=1.3.0)
Requires-Dist: numpy (>=1.16.4)
Requires-Dist: pandas (>=0.24.2)
Requires-Dist: scikit-learn (>=0.21.2)
Requires-Dist: keras (>=2.2.4)
Requires-Dist: shap (>=0.29.3)
Requires-Dist: matplotlib (>=3.1.0)
Requires-Dist: numba (>=0.43.1)
Requires-Dist: joblib (>=0.13.2)
